soapberry/__init__.py
soapberry/browser.py
soapberry/classes.py
soapberry/helpers.py
soapberry/youtube_dl/YoutubeDL.py
soapberry/youtube_dl/__init__.py
soapberry/youtube_dl/__main__.py
soapberry/youtube_dl/aes.py
soapberry/youtube_dl/cache.py
soapberry/youtube_dl/compat.py
soapberry/youtube_dl/jsinterp.py
soapberry/youtube_dl/options.py
soapberry/youtube_dl/socks.py
soapberry/youtube_dl/swfinterp.py
soapberry/youtube_dl/update.py
soapberry/youtube_dl/utils.py
soapberry/youtube_dl/version.py
soapberry/youtube_dl/downloader/__init__.py
soapberry/youtube_dl/downloader/common.py
soapberry/youtube_dl/downloader/dash.py
soapberry/youtube_dl/downloader/external.py
soapberry/youtube_dl/downloader/f4m.py
soapberry/youtube_dl/downloader/fragment.py
soapberry/youtube_dl/downloader/hls.py
soapberry/youtube_dl/downloader/http.py
soapberry/youtube_dl/downloader/ism.py
soapberry/youtube_dl/downloader/rtmp.py
soapberry/youtube_dl/downloader/rtsp.py
soapberry/youtube_dl/extractor/__init__.py
soapberry/youtube_dl/extractor/abc.py
soapberry/youtube_dl/extractor/abcnews.py
soapberry/youtube_dl/extractor/abcotvs.py
soapberry/youtube_dl/extractor/academicearth.py
soapberry/youtube_dl/extractor/acast.py
soapberry/youtube_dl/extractor/adn.py
soapberry/youtube_dl/extractor/adobeconnect.py
soapberry/youtube_dl/extractor/adobepass.py
soapberry/youtube_dl/extractor/adobetv.py
soapberry/youtube_dl/extractor/adultswim.py
soapberry/youtube_dl/extractor/aenetworks.py
soapberry/youtube_dl/extractor/afreecatv.py
soapberry/youtube_dl/extractor/airmozilla.py
soapberry/youtube_dl/extractor/aliexpress.py
soapberry/youtube_dl/extractor/aljazeera.py
soapberry/youtube_dl/extractor/allocine.py
soapberry/youtube_dl/extractor/alphaporno.py
soapberry/youtube_dl/extractor/amara.py
soapberry/youtube_dl/extractor/amcnetworks.py
soapberry/youtube_dl/extractor/americastestkitchen.py
soapberry/youtube_dl/extractor/amp.py
soapberry/youtube_dl/extractor/animeondemand.py
soapberry/youtube_dl/extractor/anvato.py
soapberry-0.0.23.dist-info/METADATA
soapberry-0.0.23.dist-info/WHEEL
soapberry-0.0.23.dist-info/top_level.txt
soapberry-0.0.23.dist-info/RECORD
