Metadata-Version: 2.1
Name: soapberry
Version: 0.0.23
Summary: soapberry
Home-page: UNKNOWN
Author: Floris Heyvaert
Author-email: UNKNOWN
License: UNKNOWN
Keywords: python,soapberry
Platform: UNKNOWN
